smtpapi/VERSION.txt
smtpapi/__init__.py
smtpapi-0.4.11.dist-info/LICENSE
smtpapi-0.4.11.dist-info/METADATA
smtpapi-0.4.11.dist-info/WHEEL
smtpapi-0.4.11.dist-info/top_level.txt
smtpapi-0.4.11.dist-info/RECORD
