Metadata-Version: 2.1
Name: smtpapi
Version: 0.4.11
Summary: Simple wrapper to use SendGrid SMTP API
Home-page: https://github.com/sendgrid/smtpapi-python/
Author: Yamil Asusta, Kane Kim
Author-email: yamil@sendgrid.com, kane.isturm@sendgrid.com
License: MIT License
Platform: UNKNOWN
Classifier: Programming Language :: Python :: 2.7
Classifier: Programming Language :: Python :: 3.4
Classifier: Programming Language :: Python :: 3.5
Classifier: Programming Language :: Python :: 3.6
Classifier: Programming Language :: Python :: 3.7
Classifier: Programming Language :: Python :: 3.8
Classifier: Programming Language :: Python :: 3.9
Classifier: Programming Language :: Python :: 3.10
License-File: LICENSE
